test/__init__.py
test/sample_test.py
thegmu_pypi_template/__init__.py
thegmu_pypi_template/sample.py
thegmu_pypi_template-1.3.0.data/scripts/thegmu-pypi-template
thegmu_pypi_template-1.3.0.dist-info/LICENSE.txt
thegmu_pypi_template-1.3.0.dist-info/METADATA
thegmu_pypi_template-1.3.0.dist-info/WHEEL
thegmu_pypi_template-1.3.0.dist-info/top_level.txt
thegmu_pypi_template-1.3.0.dist-info/RECORD
