Metadata-Version: 2.1
Name: thegmu-pypi-template
Version: 1.3.0
Summary: The GMU PyPi template repository.
Home-page: https://bitbucket.org/thegmu/thegmu-pypi-template
Author: Mybrid Wonderful, The GMU
License: MIT
Keywords: thegmu-pypi-template
Platform: UNKNOWN
Classifier: Environment :: Console
Classifier: Development Status :: 5 - Production/Stable
Classifier: Intended Audience :: Developers
Classifier: Intended Audience :: System Administrators
Classifier: Topic :: Software Development
Classifier: License :: OSI Approved :: MIT License
Classifier: Programming Language :: Python
Classifier: Programming Language :: Python :: 3.6
